terminal_translator/config.py
terminal_translator/main.py
terminal_translator/version.py
tt_terminal_translator-0.2.1.dist-info/LICENSE
tt_terminal_translator-0.2.1.dist-info/METADATA
tt_terminal_translator-0.2.1.dist-info/WHEEL
tt_terminal_translator-0.2.1.dist-info/entry_points.txt
tt_terminal_translator-0.2.1.dist-info/RECORD
