Metadata-Version: 2.1
Name: tt-terminal-translator
Version: 0.2.1
Summary: Terminal Translator is a translation CLI that uses the Google Cloud API. 
Author: gbPagano
Author-email: guilhermebpagano@gmail.com
Requires-Python: >=3.10,<4.0
Classifier: Development Status :: 5 - Production/Stable
Classifier: Environment :: Console
Classifier: Programming Language :: Python :: 3
Classifier: Programming Language :: Python :: 3.10
Classifier: Programming Language :: Python :: 3.11
Classifier: Programming Language :: Python :: 3.12
Requires-Dist: dynaconf (>=3.1.12,<4.0.0)
Requires-Dist: google-cloud-translate (>=3.11.0,<4.0.0)
Requires-Dist: pymdown-extensions (>=10.0.1,<11.0.0)
Requires-Dist: pyperclip (>=1.8.2,<2.0.0)
Requires-Dist: requests (>=2.31.0,<3.0.0)
Requires-Dist: rich (>=13.3.2,<14.0.0)
Requires-Dist: toml (>=0.10.2,<0.11.0)
Requires-Dist: typer (>=0.7.0,<0.8.0)
Project-URL: Code, https://github.com/gbPagano/terminal-translator
Project-URL: Documentation, https://terminal-translator.readthedocs.io/en/latest/
